{
    "image": {
        "date": "20201209",
        "path": "S2-N6001M00001",
        "filename": "S2-N6001M00938.jpg",
        "copyrighter": "\ubbf8\ub514\uc5b4\uadf8\ub8f9\uc0ac\ub78c\uacfc\uc232(\ucee8)",
        "H_DPI": 96,
        "location": "60",
        "V_DPI": 96,
        "bit": "24",
        "resolution": [
            1920,
            1080
        ]
    },
    "annotations": [
        {
            "data ID": "S2",
            "middle classification": "10",
            "class": "60",
            "keypoints": [
                [
                    1064,
                    481,
                    2
                ],
                [
                    972,
                    440,
                    2
                ],
                [
                    1057,
                    538,
                    2
                ],
                [
                    930,
                    497,
                    2
                ],
                [
                    1010,
                    617,
                    2
                ],
                [
                    878,
                    561,
                    2
                ],
                [
                    996,
                    589,
                    2
                ],
                [
                    943,
                    549,
                    2
                ],
                [
                    919,
                    685,
                    2
                ],
                [
                    851,
                    637,
                    2
                ],
                [
                    907,
                    750,
                    2
                ],
                [
                    797,
                    733,
                    2
                ]
            ]
        }
    ]
}