{
    "image": {
        "date": "20201209",
        "path": "S2-N6001M00001",
        "filename": "S2-N6001M01207.jpg",
        "copyrighter": "\ubbf8\ub514\uc5b4\uadf8\ub8f9\uc0ac\ub78c\uacfc\uc232(\ucee8)",
        "H_DPI": 96,
        "location": "60",
        "V_DPI": 96,
        "bit": "24",
        "resolution": [
            1920,
            1080
        ]
    },
    "annotations": [
        {
            "data ID": "S2",
            "middle classification": "10",
            "class": "60",
            "keypoints": [
                [
                    914,
                    415,
                    2
                ],
                [
                    786,
                    378,
                    2
                ],
                [
                    900,
                    518,
                    2
                ],
                [
                    761,
                    462,
                    2
                ],
                [
                    846,
                    570,
                    1
                ],
                [
                    730,
                    544,
                    2
                ],
                [
                    847,
                    571,
                    2
                ],
                [
                    781,
                    531,
                    2
                ],
                [
                    757,
                    677,
                    2
                ],
                [
                    686,
                    634,
                    2
                ],
                [
                    753,
                    769,
                    2
                ],
                [
                    632,
                    735,
                    2
                ]
            ]
        }
    ]
}