{
    "image": {
        "date": "20201209",
        "path": "S2-N6001M00001",
        "filename": "S2-N6001M00218.jpg",
        "copyrighter": "\ubbf8\ub514\uc5b4\uadf8\ub8f9\uc0ac\ub78c\uacfc\uc232(\ucee8)",
        "H_DPI": 96,
        "location": "60",
        "V_DPI": 96,
        "bit": "24",
        "resolution": [
            1920,
            1080
        ]
    },
    "annotations": [
        {
            "data ID": "S2",
            "middle classification": "10",
            "class": "60",
            "keypoints": [
                [
                    904,
                    42,
                    2
                ],
                [
                    793,
                    40,
                    2
                ],
                [
                    853,
                    112,
                    1
                ],
                [
                    775,
                    157,
                    2
                ],
                [
                    789,
                    189,
                    1
                ],
                [
                    746,
                    244,
                    2
                ],
                [
                    902,
                    250,
                    2
                ],
                [
                    851,
                    297,
                    2
                ],
                [
                    860,
                    393,
                    2
                ],
                [
                    810,
                    425,
                    2
                ],
                [
                    969,
                    479,
                    2
                ],
                [
                    836,
                    564,
                    2
                ]
            ]
        }
    ]
}