{
    "image": {
        "date": "20201209",
        "path": "S2-N6001M00001",
        "filename": "S2-N6001M00214.jpg",
        "copyrighter": "\ubbf8\ub514\uc5b4\uadf8\ub8f9\uc0ac\ub78c\uacfc\uc232(\ucee8)",
        "H_DPI": 96,
        "location": "60",
        "V_DPI": 96,
        "bit": "24",
        "resolution": [
            1920,
            1080
        ]
    },
    "annotations": [
        {
            "data ID": "S2",
            "middle classification": "10",
            "class": "60",
            "keypoints": [
                [
                    995,
                    339,
                    2
                ],
                [
                    923,
                    324,
                    1
                ],
                [
                    1018,
                    451,
                    2
                ],
                [
                    902,
                    434,
                    1
                ],
                [
                    1002,
                    450,
                    1
                ],
                [
                    964,
                    442,
                    2
                ],
                [
                    850,
                    365,
                    2
                ],
                [
                    791,
                    346,
                    2
                ],
                [
                    893,
                    489,
                    2
                ],
                [
                    791,
                    487,
                    2
                ],
                [
                    841,
                    449,
                    2
                ],
                [
                    742,
                    428,
                    2
                ]
            ]
        }
    ]
}