{
    "image": {
        "date": "20201209",
        "path": "S2-N6001M00001",
        "filename": "S2-N6001M01283.jpg",
        "copyrighter": "\ubbf8\ub514\uc5b4\uadf8\ub8f9\uc0ac\ub78c\uacfc\uc232(\ucee8)",
        "H_DPI": 96,
        "location": "60",
        "V_DPI": 96,
        "bit": "24",
        "resolution": [
            1920,
            1080
        ]
    },
    "annotations": [
        {
            "data ID": "S2",
            "middle classification": "10",
            "class": "60",
            "keypoints": [
                [
                    707,
                    383,
                    2
                ],
                [
                    669,
                    378,
                    2
                ],
                [
                    682,
                    461,
                    2
                ],
                [
                    662,
                    461,
                    1
                ],
                [
                    723,
                    530,
                    2
                ],
                [
                    685,
                    517,
                    1
                ],
                [
                    695,
                    545,
                    2
                ],
                [
                    642,
                    535,
                    2
                ],
                [
                    757,
                    663,
                    2
                ],
                [
                    700,
                    658,
                    2
                ],
                [
                    669,
                    751,
                    2
                ],
                [
                    628,
                    739,
                    2
                ]
            ]
        }
    ]
}