{
    "image": {
        "date": "20201209",
        "path": "S2-N6001M00001",
        "filename": "S2-N6001M01514.jpg",
        "copyrighter": "\ubbf8\ub514\uc5b4\uadf8\ub8f9\uc0ac\ub78c\uacfc\uc232(\ucee8)",
        "H_DPI": 96,
        "location": "60",
        "V_DPI": 96,
        "bit": "24",
        "resolution": [
            1920,
            1080
        ]
    },
    "annotations": [
        {
            "data ID": "S2",
            "middle classification": "10",
            "class": "60",
            "keypoints": [
                [
                    916,
                    277,
                    2
                ],
                [
                    830,
                    261,
                    2
                ],
                [
                    916,
                    349,
                    2
                ],
                [
                    797,
                    308,
                    1
                ],
                [
                    930,
                    413,
                    2
                ],
                [
                    800,
                    375,
                    1
                ],
                [
                    870,
                    321,
                    2
                ],
                [
                    806,
                    328,
                    2
                ],
                [
                    905,
                    374,
                    2
                ],
                [
                    831,
                    399,
                    1
                ],
                [
                    844,
                    417,
                    2
                ],
                [
                    805,
                    396,
                    2
                ]
            ]
        }
    ]
}