{
    "image": {
        "date": "20201209",
        "path": "S2-N6001M00001",
        "filename": "S2-N6001M00729.jpg",
        "copyrighter": "\ubbf8\ub514\uc5b4\uadf8\ub8f9\uc0ac\ub78c\uacfc\uc232(\ucee8)",
        "H_DPI": 96,
        "location": "60",
        "V_DPI": 96,
        "bit": "24",
        "resolution": [
            1920,
            1080
        ]
    },
    "annotations": [
        {
            "data ID": "S2",
            "middle classification": "10",
            "class": "60",
            "keypoints": [
                [
                    1190,
                    522,
                    2
                ],
                [
                    1244,
                    541,
                    2
                ],
                [
                    1169,
                    570,
                    2
                ],
                [
                    1230,
                    578,
                    2
                ],
                [
                    1173,
                    621,
                    2
                ],
                [
                    1228,
                    609,
                    2
                ],
                [
                    1136,
                    537,
                    2
                ],
                [
                    1150,
                    582,
                    2
                ],
                [
                    1041,
                    567,
                    2
                ],
                [
                    1086,
                    622,
                    2
                ],
                [
                    971,
                    574,
                    2
                ],
                [
                    1055,
                    597,
                    2
                ]
            ]
        }
    ]
}