{
    "image": {
        "date": "20201207",
        "path": "S2-N4601M00001",
        "filename": "S2-N4601M00154.jpg",
        "copyrighter": "\ubbf8\ub514\uc5b4\uadf8\ub8f9\uc0ac\ub78c\uacfc\uc232(\ucee8)",
        "H_DPI": 96,
        "location": "46",
        "V_DPI": 96,
        "bit": "24",
        "resolution": [
            1920,
            1080
        ]
    },
    "annotations": [
        {
            "data ID": "S2",
            "middle classification": "08",
            "class": "46",
            "keypoints": [
                [
                    1399,
                    677,
                    2
                ],
                [
                    1441,
                    633,
                    2
                ],
                [
                    1404,
                    700,
                    2
                ],
                [
                    1475,
                    698,
                    2
                ],
                [
                    1416,
                    730,
                    2
                ],
                [
                    1478,
                    770,
                    2
                ],
                [
                    1454,
                    740,
                    2
                ],
                [
                    1476,
                    730,
                    2
                ],
                [
                    1457,
                    785,
                    2
                ],
                [
                    1510,
                    774,
                    2
                ],
                [
                    1471,
                    836,
                    2
                ],
                [
                    1515,
                    837,
                    2
                ]
            ]
        }
    ]
}