{
    "image": {
        "date": "20201207",
        "path": "S2-N4601M00001",
        "filename": "S2-N4601M00086.jpg",
        "copyrighter": "\ubbf8\ub514\uc5b4\uadf8\ub8f9\uc0ac\ub78c\uacfc\uc232(\ucee8)",
        "H_DPI": 96,
        "location": "46",
        "V_DPI": 96,
        "bit": "24",
        "resolution": [
            1920,
            1080
        ]
    },
    "annotations": [
        {
            "data ID": "S2",
            "middle classification": "08",
            "class": "46",
            "keypoints": [
                [
                    1321,
                    357,
                    2
                ],
                [
                    1432,
                    298,
                    2
                ],
                [
                    1329,
                    406,
                    2
                ],
                [
                    1469,
                    352,
                    2
                ],
                [
                    1338,
                    460,
                    1
                ],
                [
                    1499,
                    386,
                    2
                ],
                [
                    1379,
                    426,
                    2
                ],
                [
                    1435,
                    400,
                    2
                ],
                [
                    1408,
                    519,
                    2
                ],
                [
                    1467,
                    536,
                    2
                ],
                [
                    1532,
                    584,
                    2
                ],
                [
                    1491,
                    636,
                    2
                ]
            ]
        }
    ]
}