{
    "image": {
        "date": "20201207",
        "path": "S2-N4601M00001",
        "filename": "S2-N4601M00045.jpg",
        "copyrighter": "\ubbf8\ub514\uc5b4\uadf8\ub8f9\uc0ac\ub78c\uacfc\uc232(\ucee8)",
        "H_DPI": 96,
        "location": "46",
        "V_DPI": 96,
        "bit": "24",
        "resolution": [
            1920,
            1080
        ]
    },
    "annotations": [
        {
            "data ID": "S2",
            "middle classification": "08",
            "class": "46",
            "keypoints": [
                [
                    1216,
                    375,
                    1
                ],
                [
                    1252,
                    407,
                    2
                ],
                [
                    1257,
                    348,
                    1
                ],
                [
                    1300,
                    411,
                    2
                ],
                [
                    1297,
                    362,
                    1
                ],
                [
                    1369,
                    426,
                    2
                ],
                [
                    1297,
                    296,
                    2
                ],
                [
                    1335,
                    342,
                    2
                ],
                [
                    1376,
                    256,
                    2
                ],
                [
                    1380,
                    305,
                    2
                ],
                [
                    1448,
                    177,
                    2
                ],
                [
                    1465,
                    255,
                    2
                ]
            ]
        }
    ]
}