{
    "image": {
        "date": "20201207",
        "path": "S2-N4601M00001",
        "filename": "S2-N4601M00596.jpg",
        "copyrighter": "\ubbf8\ub514\uc5b4\uadf8\ub8f9\uc0ac\ub78c\uacfc\uc232(\ucee8)",
        "H_DPI": 96,
        "location": "46",
        "V_DPI": 96,
        "bit": "24",
        "resolution": [
            1920,
            1080
        ]
    },
    "annotations": [
        {
            "data ID": "S2",
            "middle classification": "08",
            "class": "46",
            "keypoints": [
                [
                    1002,
                    311,
                    2
                ],
                [
                    958,
                    303,
                    2
                ],
                [
                    992,
                    344,
                    2
                ],
                [
                    918,
                    334,
                    2
                ],
                [
                    972,
                    390,
                    2
                ],
                [
                    899,
                    356,
                    2
                ],
                [
                    952,
                    371,
                    2
                ],
                [
                    920,
                    365,
                    2
                ],
                [
                    923,
                    451,
                    2
                ],
                [
                    896,
                    441,
                    2
                ],
                [
                    904,
                    516,
                    2
                ],
                [
                    890,
                    506,
                    2
                ]
            ]
        }
    ]
}